{"cameraMode":{"drawMode":0,"name":"Shaded","section":"Shading Mode"},"sceneLighting":false,"audioPlay":false,"sceneViewState":{"m_AlwaysRefresh":false,"showFog":true,"showSkybox":false,"showFlares":true,"showImageEffects":true,"showParticleSystems":true,"showVisualEffectGraphs":true,"m_FxEnabled":true},"in2DMode":false,"pivot":{"x":0.3437553644180298,"y":7.094858169555664,"z":-2.1236400604248049},"rotation":{"x":0.14533255994319917,"y":-0.7327778935432434,"z":0.16540294885635377,"w":0.6438612341880798},"size":1.7203240394592286,"orthographic":false}